<?xml version="1.0" encoding="UTF-8"?>
<mxfile host="app.diagrams.net" agent="Mozilla/5.0 (Macintosh; Intel Mac OS X 10_15_7) AppleWebKit/537.36 (KHTML, like Gecko) Chrome/141.0.0.0 Safari/537.36" version="28.2.9" pages="5">
  <diagram name="Hierarchy Chart" id="Oy8HtfjQb1JA13Lfomam">
    <mxGraphModel dx="946" dy="554" grid="1" gridSize="10" guides="1" tooltips="1" connect="1" arrows="1" fold="1" page="1" pageScale="1" pageWidth="850" pageHeight="1100" math="0" shadow="0">
      <root>
        <mxCell id="0" />
        <mxCell id="1" parent="0" />
        <mxCell id="q2a3ot4UEMf_TZ13XQ9F-1" value="main program" style="rounded=0;whiteSpace=wrap;html=1;" parent="1" vertex="1">
          <mxGeometry x="360" y="80" width="120" height="60" as="geometry" />
        </mxCell>
        <mxCell id="q2a3ot4UEMf_TZ13XQ9F-2" value="housekeeping ( )" style="rounded=0;whiteSpace=wrap;html=1;" parent="1" vertex="1">
          <mxGeometry x="210" y="180" width="120" height="60" as="geometry" />
        </mxCell>
        <mxCell id="q2a3ot4UEMf_TZ13XQ9F-3" value="detailLoop ( )" style="rounded=0;whiteSpace=wrap;html=1;" parent="1" vertex="1">
          <mxGeometry x="360" y="180" width="120" height="60" as="geometry" />
        </mxCell>
        <mxCell id="q2a3ot4UEMf_TZ13XQ9F-4" value="endOfJob ( )" style="rounded=0;whiteSpace=wrap;html=1;" parent="1" vertex="1">
          <mxGeometry x="510" y="180" width="120" height="60" as="geometry" />
        </mxCell>
        <mxCell id="q2a3ot4UEMf_TZ13XQ9F-5" value="" style="endArrow=none;html=1;rounded=0;exitX=0.5;exitY=0;exitDx=0;exitDy=0;entryX=0.5;entryY=1;entryDx=0;entryDy=0;" parent="1" source="q2a3ot4UEMf_TZ13XQ9F-3" target="q2a3ot4UEMf_TZ13XQ9F-1" edge="1">
          <mxGeometry width="50" height="50" relative="1" as="geometry">
            <mxPoint x="380" y="210" as="sourcePoint" />
            <mxPoint x="430" y="160" as="targetPoint" />
            <Array as="points" />
          </mxGeometry>
        </mxCell>
        <mxCell id="q2a3ot4UEMf_TZ13XQ9F-6" value="" style="endArrow=none;html=1;rounded=0;exitX=0.5;exitY=0;exitDx=0;exitDy=0;entryX=0.5;entryY=0;entryDx=0;entryDy=0;" parent="1" source="q2a3ot4UEMf_TZ13XQ9F-2" target="q2a3ot4UEMf_TZ13XQ9F-4" edge="1">
          <mxGeometry width="50" height="50" relative="1" as="geometry">
            <mxPoint x="380" y="210" as="sourcePoint" />
            <mxPoint x="560" y="160" as="targetPoint" />
            <Array as="points">
              <mxPoint x="270" y="160" />
              <mxPoint x="570" y="160" />
            </Array>
          </mxGeometry>
        </mxCell>
      </root>
    </mxGraphModel>
  </diagram>
  <diagram id="WuxdIL3g2-LeSchN8LLI" name="Main Program">
    <mxGraphModel dx="946" dy="554" grid="1" gridSize="10" guides="1" tooltips="1" connect="1" arrows="1" fold="1" page="1" pageScale="1" pageWidth="850" pageHeight="1100" math="0" shadow="0">
      <root>
        <mxCell id="0" />
        <mxCell id="1" parent="0" />
        <mxCell id="kjFNfAn_-f_r9AGTV7pg-3" value="" style="edgeStyle=orthogonalEdgeStyle;rounded=0;orthogonalLoop=1;jettySize=auto;html=1;" parent="1" source="kjFNfAn_-f_r9AGTV7pg-1" target="kjFNfAn_-f_r9AGTV7pg-2" edge="1">
          <mxGeometry relative="1" as="geometry" />
        </mxCell>
        <mxCell id="kjFNfAn_-f_r9AGTV7pg-1" value="Start" style="ellipse;whiteSpace=wrap;html=1;" parent="1" vertex="1">
          <mxGeometry x="90" y="30" width="120" height="80" as="geometry" />
        </mxCell>
        <mxCell id="jsCU__ceiV-ak8VQSKDX-2" value="" style="edgeStyle=orthogonalEdgeStyle;rounded=0;orthogonalLoop=1;jettySize=auto;html=1;" parent="1" source="kjFNfAn_-f_r9AGTV7pg-2" target="jsCU__ceiV-ak8VQSKDX-1" edge="1">
          <mxGeometry relative="1" as="geometry" />
        </mxCell>
        <mxCell id="kjFNfAn_-f_r9AGTV7pg-2" value="Declarations&lt;div&gt;&lt;span style=&quot;white-space: pre;&quot;&gt;&#x9;&lt;/span&gt;num numberOfHours&lt;/div&gt;&lt;div&gt;&lt;span style=&quot;white-space: pre;&quot;&gt;&#x9;&lt;/span&gt;num wholesaleCost&lt;br&gt;&lt;/div&gt;&lt;div&gt;&lt;span style=&quot;white-space: pre;&quot;&gt;&#x9;&lt;/span&gt;num hourlyRate = 30&lt;br&gt;&lt;/div&gt;&lt;div&gt;&lt;span style=&quot;white-space: pre;&quot;&gt;&#x9;&lt;/span&gt;num costOfJob&lt;br&gt;&lt;/div&gt;" style="whiteSpace=wrap;html=1;align=left;" parent="1" vertex="1">
          <mxGeometry x="20" y="160" width="260" height="130" as="geometry" />
        </mxCell>
        <mxCell id="jsCU__ceiV-ak8VQSKDX-4" value="" style="edgeStyle=orthogonalEdgeStyle;rounded=0;orthogonalLoop=1;jettySize=auto;html=1;" parent="1" source="jsCU__ceiV-ak8VQSKDX-1" target="jsCU__ceiV-ak8VQSKDX-3" edge="1">
          <mxGeometry relative="1" as="geometry" />
        </mxCell>
        <mxCell id="jsCU__ceiV-ak8VQSKDX-1" value="housekeeping ( )" style="shape=process;whiteSpace=wrap;html=1;backgroundOutline=1;align=center;" parent="1" vertex="1">
          <mxGeometry x="70" y="340" width="160" height="60" as="geometry" />
        </mxCell>
        <mxCell id="jsCU__ceiV-ak8VQSKDX-6" value="" style="edgeStyle=orthogonalEdgeStyle;rounded=0;orthogonalLoop=1;jettySize=auto;html=1;fillColor=#6d8764;strokeColor=#3A5431;" parent="1" source="jsCU__ceiV-ak8VQSKDX-3" target="jsCU__ceiV-ak8VQSKDX-5" edge="1">
          <mxGeometry relative="1" as="geometry" />
        </mxCell>
        <mxCell id="jsCU__ceiV-ak8VQSKDX-8" value="" style="edgeStyle=orthogonalEdgeStyle;rounded=0;orthogonalLoop=1;jettySize=auto;html=1;fillColor=#e51400;strokeColor=#B20000;" parent="1" source="jsCU__ceiV-ak8VQSKDX-3" target="jsCU__ceiV-ak8VQSKDX-7" edge="1">
          <mxGeometry relative="1" as="geometry" />
        </mxCell>
        <mxCell id="jsCU__ceiV-ak8VQSKDX-3" value="numberOfHours not = 0?" style="rhombus;whiteSpace=wrap;html=1;" parent="1" vertex="1">
          <mxGeometry x="70" y="450" width="160" height="140" as="geometry" />
        </mxCell>
        <mxCell id="KpdYpRsb7rH25_al4PRx-3" value="" style="edgeStyle=orthogonalEdgeStyle;rounded=0;orthogonalLoop=1;jettySize=auto;html=1;exitX=0.5;exitY=0;exitDx=0;exitDy=0;entryX=1;entryY=0.5;entryDx=0;entryDy=0;" parent="1" source="jsCU__ceiV-ak8VQSKDX-5" target="jsCU__ceiV-ak8VQSKDX-1" edge="1">
          <mxGeometry relative="1" as="geometry">
            <mxPoint x="450" y="485" as="sourcePoint" />
            <mxPoint x="250" y="360" as="targetPoint" />
            <Array as="points">
              <mxPoint x="370" y="370" />
            </Array>
          </mxGeometry>
        </mxCell>
        <mxCell id="jsCU__ceiV-ak8VQSKDX-5" value="detailLoop ( )" style="shape=process;whiteSpace=wrap;html=1;backgroundOutline=1;" parent="1" vertex="1">
          <mxGeometry x="290" y="485" width="160" height="70" as="geometry" />
        </mxCell>
        <mxCell id="jsCU__ceiV-ak8VQSKDX-10" value="" style="edgeStyle=orthogonalEdgeStyle;rounded=0;orthogonalLoop=1;jettySize=auto;html=1;" parent="1" source="jsCU__ceiV-ak8VQSKDX-7" target="jsCU__ceiV-ak8VQSKDX-9" edge="1">
          <mxGeometry relative="1" as="geometry" />
        </mxCell>
        <mxCell id="jsCU__ceiV-ak8VQSKDX-7" value="endOfJob ( )" style="shape=process;whiteSpace=wrap;html=1;backgroundOutline=1;" parent="1" vertex="1">
          <mxGeometry x="90" y="660" width="120" height="60" as="geometry" />
        </mxCell>
        <mxCell id="jsCU__ceiV-ak8VQSKDX-9" value="End" style="ellipse;whiteSpace=wrap;html=1;" parent="1" vertex="1">
          <mxGeometry x="85" y="750" width="130" height="80" as="geometry" />
        </mxCell>
        <mxCell id="cvluoHUlmCSpYClQeCnK-1" value="True" style="text;html=1;whiteSpace=wrap;strokeColor=none;fillColor=none;align=center;verticalAlign=middle;rounded=0;" parent="1" vertex="1">
          <mxGeometry x="230" y="485" width="60" height="30" as="geometry" />
        </mxCell>
        <mxCell id="KpdYpRsb7rH25_al4PRx-1" value="False" style="text;html=1;whiteSpace=wrap;strokeColor=none;fillColor=none;align=center;verticalAlign=middle;rounded=0;" parent="1" vertex="1">
          <mxGeometry x="90" y="610" width="60" height="30" as="geometry" />
        </mxCell>
      </root>
    </mxGraphModel>
  </diagram>
  <diagram id="fvuhdLgzAXNmrWzqCTWw" name="Housekeeping">
    <mxGraphModel dx="946" dy="1654" grid="1" gridSize="10" guides="1" tooltips="1" connect="1" arrows="1" fold="1" page="1" pageScale="1" pageWidth="850" pageHeight="1100" math="0" shadow="0">
      <root>
        <mxCell id="0" />
        <mxCell id="1" parent="0" />
        <mxCell id="LcbkXepwv0IlHSavVluB-1" value="" style="edgeStyle=orthogonalEdgeStyle;rounded=0;orthogonalLoop=1;jettySize=auto;html=1;entryX=0.5;entryY=0;entryDx=0;entryDy=0;" parent="1" source="LcbkXepwv0IlHSavVluB-2" target="LcbkXepwv0IlHSavVluB-14" edge="1">
          <mxGeometry relative="1" as="geometry">
            <mxPoint x="320" y="-980" as="targetPoint" />
          </mxGeometry>
        </mxCell>
        <mxCell id="LcbkXepwv0IlHSavVluB-2" value="Start housekeeping" style="ellipse;whiteSpace=wrap;html=1;" parent="1" vertex="1">
          <mxGeometry x="260" y="-1060" width="120" height="60" as="geometry" />
        </mxCell>
        <mxCell id="LcbkXepwv0IlHSavVluB-3" value="" style="edgeStyle=orthogonalEdgeStyle;rounded=0;orthogonalLoop=1;jettySize=auto;html=1;entryX=0.5;entryY=0;entryDx=0;entryDy=0;" parent="1" source="LcbkXepwv0IlHSavVluB-4" target="vmFlX2unJzlgMWBT_6c8-3" edge="1">
          <mxGeometry relative="1" as="geometry">
            <mxPoint x="320" y="-800" as="targetPoint" />
          </mxGeometry>
        </mxCell>
        <mxCell id="LcbkXepwv0IlHSavVluB-4" value="Input numberOfHours" style="shape=parallelogram;perimeter=parallelogramPerimeter;whiteSpace=wrap;html=1;fixedSize=1;" parent="1" vertex="1">
          <mxGeometry x="245" y="-880" width="150" height="60" as="geometry" />
        </mxCell>
        <mxCell id="LcbkXepwv0IlHSavVluB-11" value="Return to program" style="ellipse;whiteSpace=wrap;html=1;" parent="1" vertex="1">
          <mxGeometry x="260" y="-590" width="120" height="60" as="geometry" />
        </mxCell>
        <mxCell id="LcbkXepwv0IlHSavVluB-13" style="edgeStyle=orthogonalEdgeStyle;rounded=0;orthogonalLoop=1;jettySize=auto;html=1;" parent="1" source="LcbkXepwv0IlHSavVluB-14" target="LcbkXepwv0IlHSavVluB-4" edge="1">
          <mxGeometry relative="1" as="geometry" />
        </mxCell>
        <mxCell id="LcbkXepwv0IlHSavVluB-14" value="display &quot;Enter number of hours projected for the job:&amp;nbsp;&lt;span style=&quot;background-color: transparent; color: light-dark(rgb(0, 0, 0), rgb(255, 255, 255));&quot;&gt;&quot;&lt;/span&gt;" style="shape=parallelogram;perimeter=parallelogramPerimeter;whiteSpace=wrap;html=1;fixedSize=1;" parent="1" vertex="1">
          <mxGeometry x="158.75" y="-970" width="322.5" height="60" as="geometry" />
        </mxCell>
        <mxCell id="vmFlX2unJzlgMWBT_6c8-4" style="edgeStyle=orthogonalEdgeStyle;rounded=0;orthogonalLoop=1;jettySize=auto;html=1;entryX=0.5;entryY=0;entryDx=0;entryDy=0;" edge="1" parent="1" source="vmFlX2unJzlgMWBT_6c8-1" target="LcbkXepwv0IlHSavVluB-11">
          <mxGeometry relative="1" as="geometry" />
        </mxCell>
        <mxCell id="vmFlX2unJzlgMWBT_6c8-1" value="Input wholesaleCost" style="shape=parallelogram;perimeter=parallelogramPerimeter;whiteSpace=wrap;html=1;fixedSize=1;" vertex="1" parent="1">
          <mxGeometry x="245" y="-690" width="150" height="60" as="geometry" />
        </mxCell>
        <mxCell id="vmFlX2unJzlgMWBT_6c8-2" style="edgeStyle=orthogonalEdgeStyle;rounded=0;orthogonalLoop=1;jettySize=auto;html=1;" edge="1" parent="1" source="vmFlX2unJzlgMWBT_6c8-3" target="vmFlX2unJzlgMWBT_6c8-1">
          <mxGeometry relative="1" as="geometry" />
        </mxCell>
        <mxCell id="vmFlX2unJzlgMWBT_6c8-3" value="display &quot;Enter wholesale cost of materials:&amp;nbsp;&lt;span style=&quot;background-color: transparent; color: light-dark(rgb(0, 0, 0), rgb(255, 255, 255));&quot;&gt;&quot;&lt;/span&gt;" style="shape=parallelogram;perimeter=parallelogramPerimeter;whiteSpace=wrap;html=1;fixedSize=1;" vertex="1" parent="1">
          <mxGeometry x="158.75" y="-790" width="322.5" height="60" as="geometry" />
        </mxCell>
      </root>
    </mxGraphModel>
  </diagram>
  <diagram id="jsPDh9YK0qh8SESlM4bb" name="Detail Loop">
    <mxGraphModel dx="946" dy="554" grid="1" gridSize="10" guides="1" tooltips="1" connect="1" arrows="1" fold="1" page="1" pageScale="1" pageWidth="850" pageHeight="1100" math="0" shadow="0">
      <root>
        <mxCell id="0" />
        <mxCell id="1" parent="0" />
        <mxCell id="h3df3KQ_VhuAKM--fiDB-2" value="" style="edgeStyle=orthogonalEdgeStyle;rounded=0;orthogonalLoop=1;jettySize=auto;html=1;entryX=0.5;entryY=0;entryDx=0;entryDy=0;" parent="1" source="YPmeU2GO1fn5mA4Xp4zG-1" target="I1rG7ddtQM2ggT8_fVec-1" edge="1">
          <mxGeometry relative="1" as="geometry">
            <mxPoint x="340" y="150" as="targetPoint" />
          </mxGeometry>
        </mxCell>
        <mxCell id="YPmeU2GO1fn5mA4Xp4zG-1" value="Start detailLoop" style="ellipse;whiteSpace=wrap;html=1;" parent="1" vertex="1">
          <mxGeometry x="280" y="20" width="120" height="80" as="geometry" />
        </mxCell>
        <mxCell id="0Ca0Hftd0_cSNIYSWTPa-2" value="" style="edgeStyle=orthogonalEdgeStyle;rounded=0;orthogonalLoop=1;jettySize=auto;html=1;" parent="1" source="I1rG7ddtQM2ggT8_fVec-1" target="0Ca0Hftd0_cSNIYSWTPa-1" edge="1">
          <mxGeometry relative="1" as="geometry" />
        </mxCell>
        <mxCell id="I1rG7ddtQM2ggT8_fVec-1" value="costOfJob = (numberOfHours * hourlyRate) + (1.2 * wholesaleCost)" style="whiteSpace=wrap;html=1;" parent="1" vertex="1">
          <mxGeometry x="150" y="130" width="380" height="60" as="geometry" />
        </mxCell>
        <mxCell id="0Ca0Hftd0_cSNIYSWTPa-4" value="" style="edgeStyle=orthogonalEdgeStyle;rounded=0;orthogonalLoop=1;jettySize=auto;html=1;entryX=0.5;entryY=0;entryDx=0;entryDy=0;" parent="1" source="0Ca0Hftd0_cSNIYSWTPa-1" target="4mS5P6a3Yjc_qvSbieJM-1" edge="1">
          <mxGeometry relative="1" as="geometry">
            <mxPoint x="340" y="370" as="targetPoint" />
          </mxGeometry>
        </mxCell>
        <mxCell id="0Ca0Hftd0_cSNIYSWTPa-1" value="display &quot;Total cost: $ &quot; + costOfJob" style="shape=parallelogram;perimeter=parallelogramPerimeter;whiteSpace=wrap;html=1;fixedSize=1;" parent="1" vertex="1">
          <mxGeometry x="225" y="240" width="230" height="60" as="geometry" />
        </mxCell>
        <mxCell id="4mS5P6a3Yjc_qvSbieJM-1" value="Return to program" style="ellipse;whiteSpace=wrap;html=1;" parent="1" vertex="1">
          <mxGeometry x="245" y="360" width="190" height="80" as="geometry" />
        </mxCell>
      </root>
    </mxGraphModel>
  </diagram>
  <diagram id="4j64NXQR6Rtyayv77ii8" name="End of Job">
    <mxGraphModel dx="946" dy="554" grid="1" gridSize="10" guides="1" tooltips="1" connect="1" arrows="1" fold="1" page="1" pageScale="1" pageWidth="850" pageHeight="1100" math="0" shadow="0">
      <root>
        <mxCell id="0" />
        <mxCell id="1" parent="0" />
        <mxCell id="wV6lI_53ysJlutm1ZCpl-3" value="" style="edgeStyle=orthogonalEdgeStyle;rounded=0;orthogonalLoop=1;jettySize=auto;html=1;" parent="1" source="wV6lI_53ysJlutm1ZCpl-1" target="wV6lI_53ysJlutm1ZCpl-2" edge="1">
          <mxGeometry relative="1" as="geometry" />
        </mxCell>
        <mxCell id="wV6lI_53ysJlutm1ZCpl-1" value="Start endOfJob" style="ellipse;whiteSpace=wrap;html=1;" parent="1" vertex="1">
          <mxGeometry x="250" y="30" width="120" height="80" as="geometry" />
        </mxCell>
        <mxCell id="wV6lI_53ysJlutm1ZCpl-5" value="" style="edgeStyle=orthogonalEdgeStyle;rounded=0;orthogonalLoop=1;jettySize=auto;html=1;" parent="1" source="wV6lI_53ysJlutm1ZCpl-2" target="wV6lI_53ysJlutm1ZCpl-4" edge="1">
          <mxGeometry relative="1" as="geometry" />
        </mxCell>
        <mxCell id="wV6lI_53ysJlutm1ZCpl-2" value="display &quot;End of program.&quot;" style="shape=parallelogram;perimeter=parallelogramPerimeter;whiteSpace=wrap;html=1;fixedSize=1;" parent="1" vertex="1">
          <mxGeometry x="205" y="150" width="210" height="60" as="geometry" />
        </mxCell>
        <mxCell id="wV6lI_53ysJlutm1ZCpl-4" value="Return to program" style="ellipse;whiteSpace=wrap;html=1;" parent="1" vertex="1">
          <mxGeometry x="230" y="260" width="160" height="80" as="geometry" />
        </mxCell>
      </root>
    </mxGraphModel>
  </diagram>
</mxfile>
